sparrowApi/__init__.py
sparrowApi/api.py
sparrowApi/constant.py
sparrowApi/tool_class.py
sparrowApi-0.1.3.dist-info/METADATA
sparrowApi-0.1.3.dist-info/WHEEL
sparrowApi-0.1.3.dist-info/top_level.txt
sparrowApi-0.1.3.dist-info/RECORD
